hdl/Control_Unit.sv
module Control_Unit(
    input logic [3:0] opCode,
    input logic zero_flag,
    //Control Signals
    output logic PC_Enable, RA_Enable, Reg_const4, RegWrite_Enable, Reg_Imm, MemWrite_Enable,
    output logic [1:0] PC_RA_ALU_REG, Alu_Move_Mem, Reg_4_PC,
    output logic [2:0] ALUOP
);
    always_comb begin
        case (opCode)
            
            //Halt
            4'b0000: begin
                {PC_Enable, RA_Enable, Reg_const4, RegWrite_Enable, Reg_Imm,
                 MemWrite_Enable, PC_RA_ALU_REG, Alu_Move_Mem, Reg_4_PC, ALUOP} = {15{1'b0}};
            end

            //lui
            4'b0001: begin
                {PC_Enable, Reg_const4, RegWrite_Enable, Reg_Imm} = {4{1'b1}};
                Reg_4_PC = 2'b01;
                ALUOP = 3'b010;
                {
                    RA_Enable, PC_RA_ALU_REG, Alu_Move_Mem, MemWrite_Enable
                } = {6{1'b0}};
            end

            //ori
            4'b0010: begin
                {PC_Enable, Reg_const4, RegWrite_Enable, Reg_Imm} = {4{1'b1}};
                ALUOP = 3'b101;
                {RA_Enable, PC_RA_ALU_REG, Alu_Move_Mem, Reg_4_PC, MemWrite_Enable} = {8{1'b0}};
            end

            //Read Mem
            4'b0011: begin
                {PC_Enable, RegWrite_Enable} = {2{1'b1}};
                Alu_Move_Mem = 2'b10;
                {RA_Enable, PC_RA_ALU_REG, Reg_const4, Reg_Imm, Reg_4_PC, ALUOP, MemWrite_Enable} = {11{1'b0}};
            end

            //Write Mem
            4'b0100: begin
                {PC_Enable, MemWrite_Enable} = {2{1'b1}};
                {RA_Enable, PC_RA_ALU_REG, Reg_const4, RegWrite_Enable, Alu_Move_Mem, Reg_Imm, Reg_4_PC, ALUOP} = {13{1'b0}};
            end

            //Move
            4'b0101: begin
                {PC_Enable, RegWrite_Enable} = {2{1'b1}};
                Alu_Move_Mem = 2'b01;
                {RA_Enable, PC_RA_ALU_REG, Reg_const4, Reg_Imm, Reg_4_PC, ALUOP, MemWrite_Enable} = {11{1'b0}};
            end

            //Add
            4'b0110: begin
                {PC_Enable, RegWrite_Enable} = {2{1'b1}};
                ALUOP = 3'b001;
                {RA_Enable, PC_RA_ALU_REG, Reg_const4, Alu_Move_Mem, Reg_Imm, Reg_4_PC, MemWrite_Enable} = {10{1'b0}};
            end

            //Nand
            4'b0111: begin
                {PC_Enable, RegWrite_Enable} = {2{1'b1}};
                ALUOP = 3'b011;
                {RA_Enable, PC_RA_ALU_REG, Reg_const4, Alu_Move_Mem, Reg_Imm, Reg_4_PC, MemWrite_Enable} = {10{1'b0}};
            end

            //And
            4'b1000: begin
                {PC_Enable, RegWrite_Enable} = {2{1'b1}};
                ALUOP = 3'b100;
                {RA_Enable, PC_RA_ALU_REG, Reg_const4, Alu_Move_Mem, Reg_Imm, Reg_4_PC, MemWrite_Enable} = {10{1'b0}};
            end

            //Or
            4'b1001: begin
                {PC_Enable, RegWrite_Enable} = {2{1'b1}};
                ALUOP = 3'b101;
                {RA_Enable, PC_RA_ALU_REG, Reg_const4, Alu_Move_Mem, Reg_Imm, Reg_4_PC, MemWrite_Enable} = {10{1'b0}};
            end

            //Xor
            4'b1010: begin
                {PC_Enable, RegWrite_Enable} = {2{1'b1}};
                ALUOP = 3'b110;
                {RA_Enable, PC_RA_ALU_REG, Reg_const4, Alu_Move_Mem, Reg_Imm, Reg_4_PC, MemWrite_Enable} = {10{1'b0}};
            end

            //Call
            4'b1011: begin
                {RA_Enable, PC_RA_ALU_REG} = {3{1'b1}};
                PC_Enable = 1'b1;
                {Reg_const4, RegWrite_Enable, Alu_Move_Mem, Reg_Imm, Reg_4_PC, ALUOP, MemWrite_Enable} = {10{1'b0}};
            end

            //Call if zero
            4'b1100: begin
                PC_Enable = 1'b1;
                if(zero_flag == 1'b1) begin
                    {RA_Enable, PC_RA_ALU_REG} = {3{1'b1}};
                end else begin
                    {RA_Enable, PC_RA_ALU_REG} = {3{1'b0}};
                end
                {Reg_const4, RegWrite_Enable, Alu_Move_Mem, Reg_Imm, Reg_4_PC, ALUOP, MemWrite_Enable} = {10{1'b0}};
            end

            //Return
            4'b1101: begin
                PC_Enable = 1'b1;
                PC_RA_ALU_REG = 2'b01;
                {RA_Enable, Reg_const4, RegWrite_Enable, Alu_Move_Mem, Reg_Imm, Reg_4_PC, ALUOP, MemWrite_Enable} = {12{1'b0}};
            end

            //Branch
            4'b1110: begin
                {PC_Enable, Reg_Imm} = {2{1'b1}};
                PC_RA_ALU_REG = 2'b10;
                Reg_4_PC = 2'b10;
                ALUOP = 3'b001;
                {RA_Enable, Reg_const4, RegWrite_Enable, Alu_Move_Mem, MemWrite_Enable} = {6{1'b0}};
            end

            //Branch if zero
            4'b1111: begin
                {PC_Enable, Reg_Imm} = {2{1'b1}};
                if(zero_flag == 1'b1) begin
                    PC_RA_ALU_REG = 2'b10;
                end else begin
                    PC_RA_ALU_REG = 2'b0;
                end
                Reg_4_PC = 2'b10;
                ALUOP = 3'b001;
                {RA_Enable, Reg_const4, RegWrite_Enable, Alu_Move_Mem, MemWrite_Enable} = {6{1'b0}};
            end

            default: begin
                //Set all to zero
                PC_Enable = 1'b1;
                {RA_Enable, Reg_const4, RegWrite_Enable, Reg_Imm,
                 MemWrite_Enable, PC_RA_ALU_REG, Alu_Move_Mem, Reg_4_PC, ALUOP} = {14{1'b0}};
            end
        endcase
    end
endmodule

test/Control_Unit_tb.sv
module Control_Unit_tb();

    logic [3:0] opCode;
    logic zero_flag;
    //Outputs
    logic PC_Enable, RA_Enable, Reg_const4, RegWrite_Enable, Reg_Imm, MemWrite_Enable;
    logic [1:0] PC_RA_ALU_REG, Alu_Move_Mem, Reg_4_PC;
    logic [2:0] ALUOP;

    Control_Unit Control_Unit_dut(
        .opCode(opCode), .zero_flag(zero_flag),
        .PC_Enable(PC_Enable), .RA_Enable(RA_Enable), .Reg_const4(Reg_const4),
        .RegWrite_Enable(RegWrite_Enable), .Reg_Imm(Reg_Imm), .MemWrite_Enable(MemWrite_Enable),
        .PC_RA_ALU_REG(PC_RA_ALU_REG), .Alu_Move_Mem(Alu_Move_Mem), .Reg_4_PC(Reg_4_PC), .ALUOP(ALUOP)
    );

    reg [3:0] value;
    initial begin
        $dumpfile(".\\test\\vcd\\ALU.vcd");
        $dumpvars(0, Control_Unit_tb);

        zero_flag = 1'b1;
        opCode = 4'b0000;
        #15 opCode = 4'b0000;
        #15 opCode = 4'b0001;
        #15 opCode = 4'b0010;
        #15 opCode = 4'b0011;
        #15 opCode = 4'b0100;
        #15 opCode = 4'b0101;
        #15 opCode = 4'b0110;
        #15 opCode = 4'b0111;
        #15 opCode = 4'b1000;
        #15 opCode = 4'b1001;
        #15 opCode = 4'b1010;
        #15 opCode = 4'b1011;
        #15 opCode = 4'b1100;
        #15 opCode = 4'b1101;
        #15 opCode = 4'b1110;
        #15 opCode = 4'b1111;
    end

    initial
        $monitor("opCode: %b, MemWrite_Enable: %b", opCode, MemWrite_Enable);

endmodule

test/vcd/ALU.vcd
$date
	Sun Dec 10 02:54:14 2023
$end
$version
	Icarus Verilog
$end
$timescale
	1s
$end
$scope module Control_Unit_tb $end
$var wire 1 ! Reg_const4 $end
$var wire 1 " Reg_Imm $end
$var wire 2 # Reg_4_PC [1:0] $end
$var wire 1 $ RegWrite_Enable $end
$var wire 1 % RA_Enable $end
$var wire 2 & PC_RA_ALU_REG [1:0] $end
$var wire 1 ' PC_Enable $end
$var wire 1 ( MemWrite_Enable $end
$var wire 2 ) Alu_Move_Mem [1:0] $end
$var wire 3 * ALUOP [2:0] $end
$var reg 4 + opCode [3:0] $end
$var reg 1 , zero_flag $end
$scope module Control_Unit_dut $end
$var wire 4 - opCode [3:0] $end
$var wire 1 , zero_flag $end
$var reg 3 . ALUOP [2:0] $end
$var reg 2 / Alu_Move_Mem [1:0] $end
$var reg 1 ( MemWrite_Enable $end
$var reg 1 ' PC_Enable $end
$var reg 2 0 PC_RA_ALU_REG [1:0] $end
$var reg 1 % RA_Enable $end
$var reg 1 $ RegWrite_Enable $end
$var reg 2 1 Reg_4_PC [1:0] $end
$var reg 1 " Reg_Imm $end
$var reg 1 ! Reg_const4 $end
$upscope $end
$upscope $end
$enddefinitions $end
$comment Show the parameter values. $end
$dumpall
$end
#0
$dumpvars
b0 1
b0 0
b0 /
b0 .
b0 -
1,
b0 +
b0 *
b0 )
0(
0'
b0 &
0%
0$
b0 #
0"
0!
$end
#30
b10 *
b10 .
b1 #
b1 1
1'
1!
1$
1"
b1 +
b1 -
#45
b0 #
b0 1
b101 *
b101 .
b10 +
b10 -
#60
0!
0"
b0 *
b0 .
b10 )
b10 /
b11 +
b11 -
#75
0$
b0 )
b0 /
1(
b100 +
b100 -
#90
0(
b1 )
b1 /
1$
b101 +
b101 -
#105
b0 )
b0 /
b1 *
b1 .
b110 +
b110 -
#120
b11 *
b11 .
b111 +
b111 -
#135
b100 *
b100 .
b1000 +
b1000 -
#150
b101 *
b101 .
b1001 +
b1001 -
#165
b110 *
b110 .
b1010 +
b1010 -
#180
0$
b0 *
b0 .
1%
b11 &
b11 0
b1011 +
b1011 -
#195
b1100 +
b1100 -
#210
0%
b1 &
b1 0
b1101 +
b1101 -
#225
b1 *
b1 .
b10 #
b10 1
b10 &
b10 0
1"
b1110 +
b1110 -
#240
b1111 +
b1111 -
