hdl/Data_Memory.sv
module Data_Memory(
    input logic clk, writeEnable, readEnable, reset,
    input logic [7:0] Address, WriteData,
    output logic [7:0] Data
);
    logic [7:0] memory [255:0];

    integer i;
    always_ff @(posedge clk, posedge reset) begin
        if(reset) begin
            for (i = 0; i < 256; i = i + 1 ) begin
                memory[i] <= 8'b00000000;
            end
        end else if(writeEnable) begin
            memory[Address] <= WriteData;
        end
    end

    always_comb begin
        if(readEnable == 1'b1) begin
            Data = memory[Address];
        end else begin
            Data = 8'bz;
        end
    end
endmodule

hdl/Memory_Controller.sv
module Memory_Controller(
    input logic writeEnable,
    input logic [7:0] Address,
    output logic memReadEnable, memWriteEnable //Signals
);

    always_comb begin
        case (Address)
            default: begin
                memReadEnable = 1;
                memWriteEnable = writeEnable;
            end
        endcase
    end
endmodule

hdl/Memory.sv
module Memory(
    input logic clk, writeEnable, reset,
    input logic [7:0] Address, WriteData,
    output logic [7:0] Data
);
    //Flags for different devices
    logic DataMemoryReadEnable, DataMemoryWriteEnable;

    //Generate the signals needed for io mapping
    Memory_Controller controller(
        .writeEnable(writeEnable), .Address(Address), 
        .memReadEnable(DataMemoryReadEnable), .memWriteEnable(DataMemoryWriteEnable)
    );

    //Memory
    Data_Memory ram(
        .clk(clk), .writeEnable(DataMemoryWriteEnable), .readEnable(DataMemoryReadEnable),
        .reset(reset), .Address(Address), .WriteData(WriteData), .Data(Data)
    );
endmodule

hdl/ALU.sv
module ALU(
    input logic [7:0] input1, input2,
    input logic [2:0] op,
    output logic [7:0] result,
    output logic zero
    );

    always_comb begin
        case (op)
            3'b000: begin
                result = 8'b00000000;
            end

            //Addition
            3'b001: begin 
                result = input1 + input2;
            end

            //Shift Right
            3'b010: begin
                result = input1 << input2;
            end

            //Nand
            3'b011: begin
                result = ~(input1 & input2);
            end

            //And
            3'b100: begin
                result = input1 & input2;
            end

            //Or
            3'b101: begin
                result = input1 | input2;
            end

            3'b110: begin
                result = input1 ^ input2;
            end

            //Default similar to op 000
            default: begin
                result = 8'b00000000;
            end
        endcase
        
        //Set the zero flag if the result is zero
        if(result == 8'b00000000) begin
            zero = 1;
        end else begin
            zero = 0;
        end
    end

endmodule

hdl/Register_FIle.sv
module Register_File(
    input logic clk, RegWrite_Enable, reset,
    input logic [1:0] RegisterData1, RegisterData2, WriteRegister,
    input logic [7:0] WriteData,
    output logic [7:0] Data1, Data2
);

    logic [7:0] registers [3:0];

    always_comb begin
        Data1 = registers[RegisterData1];
        Data2 = registers[RegisterData2];
    end

    integer i;
    always_ff @( posedge clk, posedge reset) begin
        if(reset) begin
            for (i = 0; i < 4 ; i = i + 1) begin
                registers[i] <= 8'b00000000;
            end
        end else if(RegWrite_Enable) begin
            registers[WriteRegister] <= WriteData;
        end
    end

endmodule

hdl/Instruction_Memory.sv
module Instruction_Memory(
    input logic [7:0] Address,
    output logic [7:0] Instruction
);

    logic [7:0] memory [0:255];

    initial begin
        $readmemb("Y:/design/Custom Cpu/simulation/out.txt", memory);
        for (int i = 0; i < 256; i++) begin
            //$display("Memory[%0d] = %b", i, memory[i]);
        end
    end

    always_comb begin
        Instruction = memory[Address];
    end
endmodule

hdl/Register.sv
module Register(
    input logic clk, reset, writeEnable, 
    input logic [7:0] In,
    output logic [7:0] Out
);
    logic [7:0] Data;

    always_comb begin
        Out = Data;
    end

    always_ff @(posedge clk, posedge reset) begin
        if(reset) begin
            Data <= 8'b00000000;
        end else if(writeEnable) begin
            Data <= In;
        end
    end
endmodule

hdl/Datapath.sv
module Datapath(
    input logic clk, reset, 
    // Signals from the Control Unit
    input logic PC_Enable, RA_Enable, Reg_const4, RegWrite_Enable, Reg_Imm, MemWrite_Enable,
    input logic [1:0] PC_RA_ALU_REG, Alu_Move_Mem, Reg_4_PC,
    input logic [2:0] ALUOP,
    //Signals to Control Unit
    output logic zero_flag,
    output logic [3:0] opCode,

    //Signals to memory Controller
    input logic [7:0] ReadData,
    output logic [7:0] Address, WriteData
);
    //Wire to the input of PC
    logic [7:0] toPC;
    //Value of PC register
    logic [7:0] PCval, RAval;
    logic [7:0] instruction; // Instruction from Instruction Memory

    logic [1:0] toRd1, toRd2; // Wire connecting to rd1 and rd2 of Register File
    logic [3:0] imm;
    logic [7:0] toWriteData;
    logic [7:0] D1, D2; // Register Data 1 and 2 from the register file
    logic [7:0] Memout; // Output of memory 

    ////////////////////////////////////////
    ////////    Fetch   ////////////////////
    ///////////////////////////////////////
    Register PC(
        .clk(clk), .reset(reset), .writeEnable(PC_Enable), .In(toPC), .Out(PCval)
    );

    logic [7:0] pc_plus_one;
    assign pc_plus_one = PCval + 1;

    Register RA(
        .clk(clk), .reset(reset), .writeEnable(RA_Enable), .In(pc_plus_one), .Out(RAval)
    );

    always_comb begin
        if (PC_RA_ALU_REG == 2'b00) begin
            toPC = pc_plus_one;
        end else if (PC_RA_ALU_REG == 2'b01) begin
            toPC = RAval;
        end else if (PC_RA_ALU_REG == 2'b10) begin
            toPC = result; // Result of alu if branch instruction
        end else if (PC_RA_ALU_REG == 2'b11) begin
            toPC = D2; // From Register if it is a jump instruction
        end else begin
            toPC = pc_plus_one;
        end
    end

    ///////////////////////////////////////
    ////////   Decode    //////////////////
    ///////////////////////////////////////
    Instruction_Memory Inst(
        .Address(PCval), .Instruction(instruction)
    );

    always_comb begin
        if (Reg_const4 == 1'b0) begin
            toRd1 = instruction[3:2];
        end else if (Reg_const4 == 1'b1) begin
            toRd1 = 2'b11;
        end else begin
            toRd1 = instruction[3:2];
        end
    end

    assign toRd2 = instruction[1:0];
    assign imm = {{4{1'b0}}, instruction[3:0]}; // Zero Extend
    assign opCode = instruction[7:4];

    Register_File RegFile(
        .clk(clk), .RegWrite_Enable(RegWrite_Enable), .reset(reset), 
        .RegisterData1(toRd1), .RegisterData2(toRd2), .WriteRegister(toRd1),
        .WriteData(toWriteData), .Data1(D1), .Data2(D2)
    );

    ///////////////////////////////////////////////////
    //////////////    Execute    //////////////////////
    ///////////////////////////////////////////////////

    // Input to alu and output
    logic [7:0] IN1, IN2, result;

    // Multiplexers for the input of alu
    always_comb begin
        if (Reg_4_PC == 2'b00) begin
            IN2 = D1;
        end else if (Reg_4_PC == 2'b01) begin
            IN2 = 8'b00000100; //4
        end else if (Reg_4_PC == 2'b10) begin
            IN2 = PCval;
        end else begin
            IN2 = D1; // Default to the value of Register
        end

        if (Reg_Imm == 1'b0) begin
            IN1 = D2;
        end else if (Reg_Imm == 1'b1) begin
            IN1 = imm;
        end else begin
            IN1 = D2;
        end
    end

    ALU alu(
        .input1(IN1), .input2(IN2), .op(ALUOP), .result(result), .zero(zero_flag)
    );

    //////////////////////////////////////////////////
    //////////////   Memory    ///////////////////////
    //////////////////////////////////////////////////
    //Data_Memory memory(
    //    .clk(clk), .writeEnable(MemWrite_Enable), .reset(reset),
    //    .Address(D2), .WriteData(D1), .Data(Memout)
    //);
    // Send the address and data to the address bus and data bus
    assign Memout = ReadData;
    assign Address = D2;
    assign WriteData = D1;


    //////////////////////////////////////////////////
    //////////////  WriteBack    /////////////////////
    //////////////////////////////////////////////////
    //Multiplexer For toWriteData
    always_comb begin
        if(Alu_Move_Mem == 2'b00) begin
            toWriteData = result;
        end else if (Alu_Move_Mem == 2'b01) begin
            toWriteData = D2;
        end else if (Alu_Move_Mem == 2'b10) begin
            toWriteData = Memout;
        end else begin
            toWriteData = result;
        end
    end

endmodule

hdl/Control_Unit.sv
module Control_Unit(
    input logic [3:0] opCode,
    input logic zero_flag,
    //Control Signals
    output logic PC_Enable, RA_Enable, Reg_const4, RegWrite_Enable, Reg_Imm, MemWrite_Enable,
    output logic [1:0] PC_RA_ALU_REG, Alu_Move_Mem, Reg_4_PC,
    output logic [2:0] ALUOP
);
    always_comb begin
        case (opCode)
            
            //Halt
            4'b0000: begin
                {PC_Enable, RA_Enable, Reg_const4, RegWrite_Enable, Reg_Imm,
                 MemWrite_Enable, PC_RA_ALU_REG, Alu_Move_Mem, Reg_4_PC, ALUOP} = {15{1'b0}};
            end

            //lui
            4'b0001: begin
                {PC_Enable, Reg_const4, RegWrite_Enable, Reg_Imm} = {4{1'b1}};
                Reg_4_PC = 2'b01;
                ALUOP = 3'b010;
                {
                    RA_Enable, PC_RA_ALU_REG, Alu_Move_Mem, MemWrite_Enable
                } = {6{1'b0}};
            end

            //ori
            4'b0010: begin
                {PC_Enable, Reg_const4, RegWrite_Enable, Reg_Imm} = {4{1'b1}};
                ALUOP = 3'b101;
                {RA_Enable, PC_RA_ALU_REG, Alu_Move_Mem, Reg_4_PC, MemWrite_Enable} = {8{1'b0}};
            end

            //Read Mem
            4'b0011: begin
                {PC_Enable, RegWrite_Enable} = {2{1'b1}};
                Alu_Move_Mem = 2'b10;
                {RA_Enable, PC_RA_ALU_REG, Reg_const4, Reg_Imm, Reg_4_PC, ALUOP, MemWrite_Enable} = {11{1'b0}};
            end

            //Write Mem
            4'b0100: begin
                {PC_Enable, MemWrite_Enable} = {2{1'b1}};
                {RA_Enable, PC_RA_ALU_REG, Reg_const4, RegWrite_Enable, Alu_Move_Mem, Reg_Imm, Reg_4_PC, ALUOP} = {13{1'b0}};
            end

            //Move
            4'b0101: begin
                {PC_Enable, RegWrite_Enable} = {2{1'b1}};
                Alu_Move_Mem = 2'b01;
                {RA_Enable, PC_RA_ALU_REG, Reg_const4, Reg_Imm, Reg_4_PC, ALUOP, MemWrite_Enable} = {11{1'b0}};
            end

            //Add
            4'b0110: begin
                {PC_Enable, RegWrite_Enable} = {2{1'b1}};
                ALUOP = 3'b001;
                {RA_Enable, PC_RA_ALU_REG, Reg_const4, Alu_Move_Mem, Reg_Imm, Reg_4_PC, MemWrite_Enable} = {10{1'b0}};
            end

            //Nand
            4'b0111: begin
                {PC_Enable, RegWrite_Enable} = {2{1'b1}};
                ALUOP = 3'b011;
                {RA_Enable, PC_RA_ALU_REG, Reg_const4, Alu_Move_Mem, Reg_Imm, Reg_4_PC, MemWrite_Enable} = {10{1'b0}};
            end

            //And
            4'b1000: begin
                {PC_Enable, RegWrite_Enable} = {2{1'b1}};
                ALUOP = 3'b100;
                {RA_Enable, PC_RA_ALU_REG, Reg_const4, Alu_Move_Mem, Reg_Imm, Reg_4_PC, MemWrite_Enable} = {10{1'b0}};
            end

            //Or
            4'b1001: begin
                {PC_Enable, RegWrite_Enable} = {2{1'b1}};
                ALUOP = 3'b101;
                {RA_Enable, PC_RA_ALU_REG, Reg_const4, Alu_Move_Mem, Reg_Imm, Reg_4_PC, MemWrite_Enable} = {10{1'b0}};
            end

            //Xor
            4'b1010: begin
                {PC_Enable, RegWrite_Enable} = {2{1'b1}};
                ALUOP = 3'b110;
                {RA_Enable, PC_RA_ALU_REG, Reg_const4, Alu_Move_Mem, Reg_Imm, Reg_4_PC, MemWrite_Enable} = {10{1'b0}};
            end

            //Call
            4'b1011: begin
                {RA_Enable, PC_RA_ALU_REG} = {3{1'b1}};
                PC_Enable = 1'b1;
                {Reg_const4, RegWrite_Enable, Alu_Move_Mem, Reg_Imm, Reg_4_PC, ALUOP, MemWrite_Enable} = {10{1'b0}};
            end

            //Call if zero
            4'b1100: begin
                PC_Enable = 1'b1;
                if(zero_flag == 1'b1) begin
                    {RA_Enable, PC_RA_ALU_REG} = {3{1'b1}};
                end else begin
                    {RA_Enable, PC_RA_ALU_REG} = {3{1'b0}};
                end
                {Reg_const4, RegWrite_Enable, Alu_Move_Mem, Reg_Imm, Reg_4_PC, ALUOP, MemWrite_Enable} = {10{1'b0}};
            end

            //Return
            4'b1101: begin
                PC_Enable = 1'b1;
                PC_RA_ALU_REG = 2'b01;
                {RA_Enable, Reg_const4, RegWrite_Enable, Alu_Move_Mem, Reg_Imm, Reg_4_PC, ALUOP, MemWrite_Enable} = {12{1'b0}};
            end

            //Branch
            4'b1110: begin
                {PC_Enable, Reg_Imm} = {2{1'b1}};
                PC_RA_ALU_REG = 2'b10;
                Reg_4_PC = 2'b10;
                ALUOP = 3'b001;
                {RA_Enable, Reg_const4, RegWrite_Enable, Alu_Move_Mem, MemWrite_Enable} = {6{1'b0}};
            end

            //Branch if zero
            4'b1111: begin
                {PC_Enable, Reg_Imm} = {2{1'b1}};
                if(zero_flag == 1'b1) begin
                    PC_RA_ALU_REG = 2'b10;
                end else begin
                    PC_RA_ALU_REG = 2'b0;
                end
                Reg_4_PC = 2'b10;
                ALUOP = 3'b001;
                {RA_Enable, Reg_const4, RegWrite_Enable, Alu_Move_Mem, MemWrite_Enable} = {6{1'b0}};
            end

            default: begin
                //Set all to zero
                PC_Enable = 1'b1;
                {RA_Enable, Reg_const4, RegWrite_Enable, Reg_Imm,
                 MemWrite_Enable, PC_RA_ALU_REG, Alu_Move_Mem, Reg_4_PC, ALUOP} = {14{1'b0}};
            end
        endcase
    end
endmodule

hdl/CPU.sv
module CPU(
    input logic clk, reset, 
    input logic [7:0] ReadDataBus,
    output logic [7:0] WriteDataBus,
    output logic [7:0] AddressBus,
    output logic MemwriteEnable
);
    // From Datapath
    logic zero_flag;
    logic [3:0] opCode;

    //From Control Unit
    logic PC_Enable, RA_Enable, Reg_const4, RegWrite_Enable, Reg_Imm, MemWrite_Enable;
    logic [1:0] PC_RA_ALU_REG, Alu_Move_Mem, Reg_4_PC;
    logic [2:0] ALUOP;

    Control_Unit ctrl(
        .opCode(opCode), .zero_flag(zero_flag), //Inputs
        .PC_Enable(PC_Enable), .RA_Enable(RA_Enable), .Reg_const4(Reg_const4),
        .RegWrite_Enable(RegWrite_Enable), .Reg_Imm(Reg_Imm), .MemWrite_Enable(MemwriteEnable),
        .PC_RA_ALU_REG(PC_RA_ALU_REG), .Alu_Move_Mem(Alu_Move_Mem), .Reg_4_PC(Reg_4_PC), .ALUOP(ALUOP)
    );

    Datapath dp(
        .clk(clk), .reset(reset), .PC_Enable(PC_Enable), .RA_Enable(RA_Enable), .Reg_const4(Reg_const4),
        .RegWrite_Enable(RegWrite_Enable), .Reg_Imm(Reg_Imm), .MemWrite_Enable(MemWrite_Enable), 
        .PC_RA_ALU_REG(PC_RA_ALU_REG), .Alu_Move_Mem(Alu_Move_Mem), .Reg_4_PC(Reg_4_PC),
        .ALUOP(ALUOP), .zero_flag(zero_flag), .opCode(opCode),
        .ReadData(ReadDataBus), .Address(AddressBus), .WriteData(WriteDataBus)
    );

endmodule

hdl/Machine.sv
module Machine(
    input logic clk, reset
);

    logic [7:0] ReadDataBus, WriteDataBus, AddressBus;
    logic writeEnable; 

    // Main Cpu
    CPU cpu(
        .clk(clk), .reset(reset), .ReadDataBus(ReadDataBus), .WriteDataBus(WriteDataBus), .AddressBus(AddressBus),
        .MemwriteEnable(writeEnable)
    );

    //Memory
    Memory mem(
        .clk(clk), .writeEnable(writeEnable), .reset(reset), .Address(AddressBus), .WriteData(WriteDataBus), .Data(ReadDataBus)
    );

endmodule

test/Machine_tb.sv
module Machine_tb();

    logic clk, reset;

    Machine computer(
        .clk(clk), .reset(reset)
    );

    initial begin
        $dumpfile(".\\test\\vcd\\Machine.vcd");
        $dumpvars(0, Machine_tb);

        #15 clk = 0; reset = 0;
        #15 clk = 1; reset = 1;
        #15 clk = 0; reset = 0;
        #15 clk = 1; #15 clk = 0; 
        #15 clk = 1; #15 clk = 0; 
        #15 clk = 1; #15 clk = 0; 
        #15 clk = 1; #15 clk = 0; 
        #15 clk = 1; #15 clk = 0; 
        #15 clk = 1; #15 clk = 0; 
        #15 clk = 1; #15 clk = 0; 
        #15 clk = 1; #15 clk = 0; 
        #15 clk = 1; #15 clk = 0; 
        #15 clk = 1; #15 clk = 0; 
        #15 clk = 1; #15 clk = 0; 
        #15 clk = 1; #15 clk = 0; 
        #15 clk = 1; #15 clk = 0; 
        #15 clk = 1; #15 clk = 0; 
        #15 clk = 1; #15 clk = 0; 
        #15 clk = 1; #15 clk = 0; 
        #15 clk = 1; #15 clk = 0; 
        #15 clk = 1; #15 clk = 0; 
        #15 clk = 1; #15 clk = 0; 
        #15 clk = 1; #15 clk = 0; 
        #15 clk = 1; #15 clk = 0; 
        #15 clk = 1; #15 clk = 0; 
        #15 clk = 1; #15 clk = 0; 
        #15 clk = 1; #15 clk = 0; 
    end

    initial
        $monitor("clk: %b", clk);
endmodule

test/vcd/Machine.vcd
$date
	Sun Dec 10 20:40:19 2023
$end
$version
	Icarus Verilog
$end
$timescale
	1s
$end
$scope module Machine_tb $end
$var reg 1 ! clk $end
$var reg 1 " reset $end
$scope module computer $end
$var wire 1 ! clk $end
$var wire 1 " reset $end
$var wire 1 # writeEnable $end
$var wire 8 $ WriteDataBus [7:0] $end
$var wire 8 % ReadDataBus [7:0] $end
$var wire 8 & AddressBus [7:0] $end
$scope module cpu $end
$var wire 1 ! clk $end
$var wire 1 " reset $end
$var wire 1 ' zero_flag $end
$var wire 4 ( opCode [3:0] $end
$var wire 8 ) WriteDataBus [7:0] $end
$var wire 1 * Reg_const4 $end
$var wire 1 + Reg_Imm $end
$var wire 2 , Reg_4_PC [1:0] $end
$var wire 1 - RegWrite_Enable $end
$var wire 8 . ReadDataBus [7:0] $end
$var wire 1 / RA_Enable $end
$var wire 2 0 PC_RA_ALU_REG [1:0] $end
$var wire 1 1 PC_Enable $end
$var wire 1 # MemwriteEnable $end
$var wire 2 2 Alu_Move_Mem [1:0] $end
$var wire 8 3 AddressBus [7:0] $end
$var wire 3 4 ALUOP [2:0] $end
$var reg 1 5 MemWrite_Enable $end
$scope module ctrl $end
$var wire 1 ' zero_flag $end
$var wire 4 6 opCode [3:0] $end
$var reg 3 7 ALUOP [2:0] $end
$var reg 2 8 Alu_Move_Mem [1:0] $end
$var reg 1 # MemWrite_Enable $end
$var reg 1 1 PC_Enable $end
$var reg 2 9 PC_RA_ALU_REG [1:0] $end
$var reg 1 / RA_Enable $end
$var reg 1 - RegWrite_Enable $end
$var reg 2 : Reg_4_PC [1:0] $end
$var reg 1 + Reg_Imm $end
$var reg 1 * Reg_const4 $end
$upscope $end
$scope module dp $end
$var wire 3 ; ALUOP [2:0] $end
$var wire 8 < Address [7:0] $end
$var wire 2 = Alu_Move_Mem [1:0] $end
$var wire 1 5 MemWrite_Enable $end
$var wire 8 > Memout [7:0] $end
$var wire 1 1 PC_Enable $end
$var wire 2 ? PC_RA_ALU_REG [1:0] $end
$var wire 1 / RA_Enable $end
$var wire 1 - RegWrite_Enable $end
$var wire 2 @ Reg_4_PC [1:0] $end
$var wire 1 + Reg_Imm $end
$var wire 1 * Reg_const4 $end
$var wire 8 A WriteData [7:0] $end
$var wire 1 ! clk $end
$var wire 1 " reset $end
$var wire 1 ' zero_flag $end
$var wire 2 B toRd2 [1:0] $end
$var wire 8 C result [7:0] $end
$var wire 8 D pc_plus_one [7:0] $end
$var wire 4 E opCode [3:0] $end
$var wire 8 F instruction [7:0] $end
$var wire 4 G imm [3:0] $end
$var wire 8 H ReadData [7:0] $end
$var wire 8 I RAval [7:0] $end
$var wire 8 J PCval [7:0] $end
$var wire 8 K D2 [7:0] $end
$var wire 8 L D1 [7:0] $end
$var reg 8 M IN1 [7:0] $end
$var reg 8 N IN2 [7:0] $end
$var reg 8 O toPC [7:0] $end
$var reg 2 P toRd1 [1:0] $end
$var reg 8 Q toWriteData [7:0] $end
$scope module Inst $end
$var wire 8 R Address [7:0] $end
$var reg 8 S Instruction [7:0] $end
$scope begin $ivl_for_loop0 $end
$var integer 32 T i [31:0] $end
$upscope $end
$upscope $end
$scope module PC $end
$var wire 8 U In [7:0] $end
$var wire 1 ! clk $end
$var wire 1 " reset $end
$var wire 1 1 writeEnable $end
$var reg 8 V Data [7:0] $end
$var reg 8 W Out [7:0] $end
$upscope $end
$scope module RA $end
$var wire 8 X In [7:0] $end
$var wire 1 ! clk $end
$var wire 1 " reset $end
$var wire 1 / writeEnable $end
$var reg 8 Y Data [7:0] $end
$var reg 8 Z Out [7:0] $end
$upscope $end
$scope module RegFile $end
$var wire 1 - RegWrite_Enable $end
$var wire 2 [ RegisterData1 [1:0] $end
$var wire 2 \ RegisterData2 [1:0] $end
$var wire 8 ] WriteData [7:0] $end
$var wire 2 ^ WriteRegister [1:0] $end
$var wire 1 ! clk $end
$var wire 1 " reset $end
$var reg 8 _ Data1 [7:0] $end
$var reg 8 ` Data2 [7:0] $end
$var integer 32 a i [31:0] $end
$upscope $end
$scope module alu $end
$var wire 8 b input1 [7:0] $end
$var wire 8 c input2 [7:0] $end
$var wire 3 d op [2:0] $end
$var reg 8 e result [7:0] $end
$var reg 1 ' zero $end
$upscope $end
$upscope $end
$upscope $end
$scope module mem $end
$var wire 8 f Address [7:0] $end
$var wire 8 g WriteData [7:0] $end
$var wire 1 ! clk $end
$var wire 1 " reset $end
$var wire 1 # writeEnable $end
$var wire 1 h DataMemoryWriteEnable $end
$var wire 1 i DataMemoryReadEnable $end
$var wire 8 j Data [7:0] $end
$scope module controller $end
$var wire 8 k Address [7:0] $end
$var wire 1 # writeEnable $end
$var reg 1 i memReadEnable $end
$var reg 1 h memWriteEnable $end
$upscope $end
$scope module ram $end
$var wire 8 l Address [7:0] $end
$var wire 8 m WriteData [7:0] $end
$var wire 1 ! clk $end
$var wire 1 i readEnable $end
$var wire 1 " reset $end
$var wire 1 h writeEnable $end
$var reg 8 n Data [7:0] $end
$var integer 32 o i [31:0] $end
$upscope $end
$upscope $end
$upscope $end
$upscope $end
$enddefinitions $end
$comment Show the parameter values. $end
$dumpall
$end
#0
$dumpvars
bx o
bx n
bx m
bx l
bx k
bx j
1i
0h
bx g
bx f
b0 e
b0 d
bx c
bx b
bx a
bx `
bx _
bx ^
b0 ]
bx \
bx [
bx Z
bx Y
bx X
bx W
bx V
bx U
b100000000 T
bx S
bx R
b0 Q
bx P
bx O
bx N
bx M
bx L
bx K
bx J
bx I
bx H
bx G
bx F
bx E
bx D
b0 C
bx B
bx A
b0 @
b0 ?
bx >
b0 =
bx <
b0 ;
b0 :
b0 9
b0 8
b0 7
bx 6
x5
b0 4
bx 3
b0 2
11
b0 0
0/
bx .
0-
b0 ,
0+
0*
bx )
bx (
1'
bx &
bx %
bx $
0#
x"
x!
$end
#15
0"
0!
#30
b0 >
b0 %
b0 .
b0 H
b0 j
b0 n
b0 M
b0 b
b100 N
b100 c
b10 4
b10 7
b10 ;
b10 d
b1 ,
b1 :
b1 @
1*
1-
1+
b0 G
b0 &
b0 3
b0 <
b0 f
b0 k
b0 l
b0 K
b0 `
b0 $
b0 )
b0 A
b0 g
b0 m
b0 L
b0 _
b1 (
b1 6
b1 E
b0 B
b0 \
b11 P
b11 [
b11 ^
b10000 F
b10000 S
b1 O
b1 U
b1 D
b1 X
b0 J
b0 R
b0 W
b0 I
b0 Z
b0 V
b0 Y
b100 a
b100000000 o
1"
1!
#45
0"
0!
#60
b1 Q
b1 ]
0'
b1 C
b1 e
b1 M
b1 b
b0 N
b0 c
b0 ,
b0 :
b0 @
b101 4
b101 7
b101 ;
b101 d
b1 G
b10 (
b10 6
b10 E
b1 B
b1 \
b10 O
b10 U
b100001 F
b100001 S
b10 D
b10 X
b1 J
b1 R
b1 W
b1 V
1!
#75
0!
#90
b0 P
b0 [
b0 ^
1'
b0 C
b0 e
0*
0+
b0 4
b0 7
b0 ;
b0 d
b1 2
b1 8
b1 =
b11 G
b1 &
b1 3
b1 <
b1 f
b1 k
b1 l
b1 K
b1 `
b101 (
b101 6
b101 E
b11 B
b11 \
b11 O
b11 U
b1010011 F
b1010011 S
b0 N
b0 c
b11 D
b11 X
b10 J
b10 R
b10 W
b0 $
b0 )
b0 A
b0 g
b0 m
b0 L
b0 _
b10 V
1!
#105
0!
#120
b0 Q
b0 ]
b11 P
b11 [
b11 ^
b0 M
b0 b
b0 2
b0 8
b0 =
b10 4
b10 7
b10 ;
b10 d
b1 ,
b1 :
b1 @
1*
1+
b0 G
b1 (
b1 6
b1 E
b0 B
b0 \
b100 O
b100 U
b100 N
b100 c
b10000 F
b10000 S
b1 $
b1 )
b1 A
b1 g
b1 m
b1 L
b1 _
b100 D
b100 X
b11 J
b11 R
b11 W
b11 V
1!
#135
0!
#150
b1110 Q
b1110 ]
0'
b1110 C
b1110 e
b1110 M
b1110 b
b0 N
b0 c
b0 ,
b0 :
b0 @
b101 4
b101 7
b101 ;
b101 d
b1110 G
b0 &
b0 3
b0 <
b0 f
b0 k
b0 l
b0 K
b0 `
b10 (
b10 6
b10 E
b10 B
b10 \
b101 O
b101 U
b101110 F
b101110 S
b101 D
b101 X
b100 J
b100 R
b100 W
b0 $
b0 )
b0 A
b0 g
b0 m
b0 L
b0 _
b100 V
1!
#165
0!
#180
b0 Q
b0 ]
b0 P
b0 [
b0 ^
1'
b0 C
b0 e
0*
0-
0+
b0 4
b0 7
b0 ;
b0 d
1/
b11 0
b11 9
b11 ?
b11 G
b1110 &
b1110 3
b1110 <
b1110 f
b1110 k
b1110 l
b1110 K
b1110 `
b1011 (
b1011 6
b1011 E
b11 B
b11 \
b1110 O
b1110 U
b1 N
b1 c
b10110011 F
b10110011 S
b1 $
b1 )
b1 A
b1 g
b1 m
b1 L
b1 _
b110 D
b110 X
b101 J
b101 R
b101 W
b101 V
1!
#195
0!
#210
b1111 Q
b1111 ]
0'
b1111 C
b1111 e
b1111 O
b1111 U
b101 M
b101 b
b1110 N
b1110 c
0/
b0 0
b0 9
b0 ?
b101 4
b101 7
b101 ;
b101 d
1*
1-
1+
b101 G
b0 &
b0 3
b0 <
b0 f
b0 k
b0 l
b0 K
b0 `
b1110 $
b1110 )
b1110 A
b1110 g
b1110 m
b1110 L
b1110 _
b10 (
b10 6
b10 E
b1 B
b1 \
b11 P
b11 [
b11 ^
b100101 F
b100101 S
b1111 D
b1111 X
b1110 J
b1110 R
b1110 W
b110 I
b110 Z
b1110 V
b110 Y
1!
#225
0!
#240
b1 P
b1 [
b1 ^
1'
b0 C
b0 e
b1111 M
b1111 b
0*
0+
b0 4
b0 7
b0 ;
b0 d
b1 2
b1 8
b1 =
b111 G
b1111 &
b1111 3
b1111 <
b1111 f
b1111 k
b1111 l
b1111 K
b1111 `
b101 (
b101 6
b101 E
b11 B
b11 \
b10000 O
b10000 U
b0 N
b0 c
b1010111 F
b1010111 S
b0 $
b0 )
b0 A
b0 g
b0 m
b0 L
b0 _
b10000 D
b10000 X
b1111 J
b1111 R
b1111 W
b1111 V
1!
#255
0!
#270
b0 Q
b0 ]
b1 M
b1 b
0-
b0 2
b0 8
b0 =
b1 0
b1 9
b1 ?
b0 G
b1 &
b1 3
b1 <
b1 f
b1 k
b1 l
b1 K
b1 `
b1101 (
b1101 6
b1101 E
b0 B
b0 \
b0 P
b0 [
b0 ^
b110 O
b110 U
b11010000 F
b11010000 S
b1 N
b1 c
b10001 D
b10001 X
b10000 J
b10000 R
b10000 W
b1 $
b1 )
b1 A
b1 g
b1 m
b1 L
b1 _
b10000 V
1!
#285
0!
#300
b10000 Q
b10000 ]
0'
b10000 C
b10000 e
b111 O
b111 U
b1111 M
b1111 b
b0 0
b0 9
b0 ?
b1 4
b1 7
b1 ;
b1 d
1-
b1 G
b1111 &
b1111 3
b1111 <
b1111 f
b1111 k
b1111 l
b1111 K
b1111 `
b110 (
b110 6
b110 E
b1 B
b1 \
b1100001 F
b1100001 S
b111 D
b111 X
b110 J
b110 R
b110 W
b110 V
1!
#315
0!
#330
1'
b11 P
b11 [
b11 ^
b0 M
b0 b
b10 4
b10 7
b10 ;
b10 d
b1 ,
b1 :
b1 @
1*
1+
b0 G
b10000 &
b10000 3
b10000 <
b10000 f
b10000 k
b10000 l
b10000 K
b10000 `
b0 Q
b0 ]
b1 (
b1 6
b1 E
b0 B
b0 \
b0 C
b0 e
b1000 O
b1000 U
b10000 F
b10000 S
b100 N
b100 c
b1000 D
b1000 X
b111 J
b111 R
b111 W
b1111 $
b1111 )
b1111 A
b1111 g
b1111 m
b1111 L
b1111 _
b111 V
1!
#345
0!
#360
b0 Q
b0 ]
b0 N
b0 c
1'
b0 C
b0 e
b0 ,
b0 :
b0 @
b101 4
b101 7
b101 ;
b101 d
b10 (
b10 6
b10 E
b1001 O
b1001 U
b100000 F
b100000 S
b0 $
b0 )
b0 A
b0 g
b0 m
b0 L
b0 _
b1001 D
b1001 X
b1000 J
b1000 R
b1000 W
b1000 V
1!
#375
0!
#390
b10000 N
b10000 c
b10000 $
b10000 )
b10000 A
b10000 g
b10000 m
b10000 L
b10000 _
b0 P
b0 [
b0 ^
1h
0*
0-
0+
b0 4
b0 7
b0 ;
b0 d
1#
b11 G
b0 &
b0 3
b0 <
b0 f
b0 k
b0 l
b0 K
b0 `
b100 (
b100 6
b100 E
b11 B
b11 \
b1010 O
b1010 U
b1000011 F
b1000011 S
b1010 D
b1010 X
b1001 J
b1001 R
b1001 W
b1001 V
1!
#405
0!
#420
b10000 M
b10000 b
0h
01
0#
b0 G
b10000 &
b10000 3
b10000 <
b10000 f
b10000 k
b10000 l
b10000 K
b10000 `
b0 (
b0 6
b0 E
b0 B
b0 \
b1011 O
b1011 U
b0 F
b0 S
b0 >
b0 %
b0 .
b0 H
b0 j
b0 n
b1011 D
b1011 X
b1010 J
b1010 R
b1010 W
b1010 V
1!
