hdl/Uart.sv
module Uart(
    input logic clk, reset, writeEnable, readEnable, rx, 
    //Pins 
    input logic [7:0] writeData,
    input logic [1:0] regSelect, 
    output logic tx,
    output logic [7:0] Data
);

    //Registers
    logic [7:0] DOUT; // Data Out
    logic [7:0] DIN; //
    logic [7:0] Status; // Set lowest bit to 1 to start sending. The second bit is set when it is sending.

    // States
    parameter s_IDLE = 2'b00;
    parameter s_START = 2'b01;
    parameter s_DATA = 2'b10;
    parameter s_STOP = 2'b11;

    logic [3:0] r_Bit_Index;
    logic [1:0] state; 
    logic stop_Index;

    always_comb begin
        if(readEnable) begin
            case (regSelect)
                2'b00: begin
                    Data = DOUT;
                end
                2'b01: begin
                    Data = DIN;
                end
                2'b10: begin
                    Data = Status;
                end
                default: begin
                    Data = DOUT;
                end
            endcase
        end else begin
            Data = 8'bz;
        end
    end
    
    always_ff @(posedge clk, posedge reset) begin
        if(reset) begin
            state <= s_IDLE;
            DOUT <= 8'b00000000;
            DIN <= 8'b00000000;
            Status <= 8'b00000000;
            r_Bit_Index <= 3'b000;
        end else if (writeEnable) begin
            case (regSelect)
                2'b00: DOUT <= writeData;
                2'b01: DIN <= writeData;
                2'b10: Status <= writeData;
                default: begin
                    DOUT <= writeData;
                end
            endcase
        end
    end

    always_ff @(posedge clk) begin
        case (state)
            s_IDLE: begin //Idle Wait for the lowest bit of Status reg to be 1 to start sending
                if(Status[0] == 1'b1) begin
                    state <= s_START;
                end else if(Status[0] == 1'b0) begin
                    state <= s_IDLE;
                end
                //tx <= 1;
                stop_Index <= 0;
            end

            s_START: begin
                Status[1] <= 1'b1; 
                //tx <= 1'b0; //First bit, must be 0
                state <= s_DATA;
                r_Bit_Index <= 3'b000;
            end

            s_DATA: begin
                if(r_Bit_Index == 3'b111) begin
                    state <= s_STOP;
                end
                //tx <= DOUT[r_Bit_Index];
                r_Bit_Index <= r_Bit_Index + 1;
            end

            s_STOP: begin
                if(stop_Index == 1'b0) begin
                    //tx <= 1'b1;
                    stop_Index <= stop_Index + 1;
                end else if(stop_Index == 1'b1) begin // CleanUp
                    //tx <= 1'b1;
                    state <= s_IDLE;
                    r_Bit_Index <= 3'b000;
                    Status <= 8'b00000000;
                    DOUT <= 8'b00000000;
                end
            end

            default: begin
                tx <= 1;
                state <= s_IDLE;
            end
        endcase
    end

    always_comb begin
        case (state)
            s_IDLE: begin
                tx = 1'b1;
            end

            s_START: begin
                tx = 1'b0;
            end

            s_DATA: begin
                tx = DOUT[r_Bit_Index];
            end

            s_STOP: begin
                tx = 1'b1;
            end
            default: begin
                tx = 1'b1;
            end
        endcase
    end
endmodule

test/Uart_tb.sv
module Uart_tb();

    logic clk, reset, writeEnable, readEnable, rx;
    logic [7:0] Data, writeData;
    logic [1:0] regselect;
    logic tx;

    Uart uart(
        .clk(clk), .reset(reset), .writeEnable(writeEnable), .readEnable(readEnable), .rx(rx),
        .Data(Data), .writeData(writeData), .regSelect(regselect), .tx(tx)
    );

    initial begin
        $dumpfile(".\\test\\vcd\\Uart.vcd");
        $dumpvars(0, Uart_tb);

        #15 clk = 0; reset = 0;
        #15 clk = 1; reset = 1;
        #15 clk = 0; reset = 0;
        #15 clk = 1; #15 clk = 0; writeEnable = 1; writeData = 8'b10101010; regselect = 2'b00;
        #15 clk = 1; #15 clk = 0; writeEnable = 1; writeData = 8'b00000001; regselect = 2'b10;
        #15 clk = 1; #15 clk = 0; writeEnable = 0;
        #15 clk = 1; #15 clk = 0; 
        #15 clk = 1; #15 clk = 0; 
        #15 clk = 1; #15 clk = 0; 
        #15 clk = 1; #15 clk = 0; 
        #15 clk = 1; #15 clk = 0; 
        #15 clk = 1; #15 clk = 0; 
        #15 clk = 1; #15 clk = 0; 
        #15 clk = 1; #15 clk = 0; 
        #15 clk = 1; #15 clk = 0; 
        #15 clk = 1; #15 clk = 0; 
        #15 clk = 1; #15 clk = 0; 
        #15 clk = 1; #15 clk = 0; 
        #15 clk = 1; #15 clk = 0; 
        #15 clk = 1; #15 clk = 0; 
        #15 clk = 1; #15 clk = 0; 
        #15 clk = 1; #15 clk = 0; 
        #15 clk = 1; #15 clk = 0; 
        #15 clk = 1; #15 clk = 0; 
        #15 clk = 1; #15 clk = 0; 
        #15 clk = 1; #15 clk = 0; 
        #15 clk = 1; #15 clk = 0; 

    end

    initial
        $monitor("clk: %b", clk);
endmodule

test/vcd/Uart.vcd
$date
	Mon Dec 11 04:17:58 2023
$end
$version
	Icarus Verilog
$end
$timescale
	1s
$end
$scope module Uart_tb $end
$var wire 1 ! tx $end
$var wire 8 " Data [7:0] $end
$var reg 1 # clk $end
$var reg 1 $ readEnable $end
$var reg 2 % regselect [1:0] $end
$var reg 1 & reset $end
$var reg 1 ' rx $end
$var reg 8 ( writeData [7:0] $end
$var reg 1 ) writeEnable $end
$scope module uart $end
$var wire 1 # clk $end
$var wire 1 $ readEnable $end
$var wire 2 * regSelect [1:0] $end
$var wire 1 & reset $end
$var wire 1 ' rx $end
$var wire 8 + writeData [7:0] $end
$var wire 1 ) writeEnable $end
$var parameter 2 , s_DATA $end
$var parameter 2 - s_IDLE $end
$var parameter 2 . s_START $end
$var parameter 2 / s_STOP $end
$var reg 8 0 DIN [7:0] $end
$var reg 8 1 DOUT [7:0] $end
$var reg 8 2 Data [7:0] $end
$var reg 8 3 Status [7:0] $end
$var reg 4 4 r_Bit_Index [3:0] $end
$var reg 2 5 state [1:0] $end
$var reg 1 6 stop_Index $end
$var reg 1 ! tx $end
$upscope $end
$upscope $end
$enddefinitions $end
$comment Show the parameter values. $end
$dumpall
b11 /
b1 .
b0 -
b10 ,
$end
#0
$dumpvars
x6
bx 5
bx 4
bx 3
bz 2
bx 1
bx 0
bx +
bx *
x)
bx (
x'
x&
bx %
x$
x#
bz "
1!
$end
#15
0&
0#
#30
b0 4
b0 3
b0 0
b0 1
b0 5
1&
1#
#45
0&
0#
#60
06
1#
#75
b0 %
b0 *
b10101010 (
b10101010 +
1)
0#
#90
b10101010 1
1#
#105
b10 %
b10 *
b1 (
b1 +
0#
#120
b1 3
1#
#135
0)
0#
#150
0!
b1 5
1#
#165
0#
#180
b10 5
b11 3
1#
#195
0#
#210
1!
b1 4
1#
#225
0#
#240
0!
b10 4
1#
#255
0#
#270
1!
b11 4
1#
#285
0#
#300
0!
b100 4
1#
#315
0#
#330
1!
b101 4
1#
#345
0#
#360
0!
b110 4
1#
#375
0#
#390
1!
b111 4
1#
#405
0#
#420
b1000 4
b11 5
1#
#435
0#
#450
16
1#
#465
0#
#480
b0 1
b0 3
b0 4
b0 5
1#
#495
0#
#510
06
1#
