hdl/Uart/Uart_Transmitter.sv
module Uart_Transmitter(
    input logic baud_clk, reset,
    input logic [7:0] Data,
    input logic start,
    output logic tx,
    output logic busy
);
    parameter DATA_BITS = 8;

    logic [2:0] data_index = 0;
    // State machine states
    parameter s_IDLE = 2'b00, s_START = 2'b01, s_DATA = 2'b10, s_STOP = 2'b11;
    logic [1:0] state = s_IDLE;

    always_ff @(posedge baud_clk or posedge reset) begin
        if (reset) begin
            state <= s_IDLE;
            data_index <= 0;
            tx <= 1'b1; // Idle state is high
            busy <= 0;
        end else begin
            case (state)
                s_IDLE : begin
                    if(start) begin
                        state <= s_START;
                    end
                    tx <= 1'b1;
                    busy <= 0;
                end
                s_START: begin
                    tx <= 1'b0; // Start bit
                    state <= s_DATA;
                    busy <= 1;
                end
                s_DATA : begin
                    tx <= Data[data_index];
                    if (data_index == DATA_BITS - 1) begin
                        state <= s_STOP;
                        data_index <= 0;
                    end else begin
                        data_index <= data_index + 1;
                    end
                end
                s_STOP : begin
                    tx <= 1'b1; // Stop bit
                    state <= s_IDLE;
                end
                default:  state <= s_IDLE;
            endcase
        end
    end
endmodule

hdl/Uart/Uarttest.sv
module Uart(
    input logic reset, writeEnable, readEnable, rx, clk,
    //Pins 
    input logic [7:0] writeData,
    input logic [1:0] regSelect, 
    output logic tx,
    output logic [7:0] Data
);
        // UART configuration parameters
    parameter DATA_BITS = 8;
    parameter STOP_BITS = 1;
    parameter DIVISOR = 4; // Adjust for your system clock and baud rate

    // UART control signals
    logic [DATA_BITS-1:0] data = 8'b01001000; // ASCII 'h'
    logic [7:0] control;
    logic [2:0] data_index = 0;
    logic [6:0] baud_counter = 0;
    logic baud_clk = 0;
    logic busy;

    // Baud rate generation
    always_ff @(posedge clk or posedge reset) begin
        if (reset) begin
            baud_counter <= 0;
            baud_clk <= 0;
        end else if (baud_counter == (DIVISOR/2) - 1) begin
            baud_clk <= ~baud_clk;
            baud_counter <= 0;
        end else begin
            baud_counter <= baud_counter + 1;
        end
    end

    always_ff @(posedge clk or posedge reset) begin
        if (reset) begin
            data <= 8'b00000000;
            control <= 8'b00000000;
        end else if (writeEnable) begin
            case (regSelect)
                2'b00 : data <= writeData;
                2'b10 : control <= writeData;
            endcase
        end else if (control[0] && busy) begin
            control <= 8'b00000000;
        end
    end

    Uart_Transmitter transmitter(
        .baud_clk(baud_clk), .reset(reset), .Data(data), .start(control[0]), .tx(tx), .busy(busy)
    );

endmodule

test/Uart_tb.sv
module Uart_tb();

    logic clk, reset, writeEnable, readEnable, rx;
    logic [7:0] Data, writeData;
    logic [1:0] regselect;
    logic tx;

    Uart uart(
        .clk(clk), .reset(reset), .writeEnable(writeEnable), .readEnable(readEnable), .rx(rx),
        .Data(Data), .writeData(writeData), .regSelect(regselect), .tx(tx)
    );

    initial begin
        $dumpfile(".\\test\\vcd\\Uart.vcd");
        $dumpvars(0, Uart_tb);

        #15 clk = 0; reset = 0;
        #15 clk = 1; reset = 1;
        #15 clk = 0; reset = 0;
        #15 clk = 1; #15 clk = 0; writeEnable = 1; writeData = 8'b10101010; regselect = 2'b00;
        #15 clk = 1; #15 clk = 0; writeEnable = 1; writeData = 8'b00000001; regselect = 2'b10;
        #15 clk = 1; #15 clk = 0; writeEnable = 0;
        #15 clk = 1; #15 clk = 0; 
        #15 clk = 1; #15 clk = 0; 
        #15 clk = 1; #15 clk = 0; 
        #15 clk = 1; #15 clk = 0; 
        #15 clk = 1; #15 clk = 0; 
        #15 clk = 1; #15 clk = 0; 
        #15 clk = 1; #15 clk = 0; 
        #15 clk = 1; #15 clk = 0; 
        #15 clk = 1; #15 clk = 0; 
        #15 clk = 1; #15 clk = 0; 
        #15 clk = 1; #15 clk = 0; 
        #15 clk = 1; #15 clk = 0; 
        #15 clk = 1; #15 clk = 0; 
        #15 clk = 1; #15 clk = 0; 
        #15 clk = 1; #15 clk = 0; 
        #15 clk = 1; #15 clk = 0; 
        #15 clk = 1; #15 clk = 0; 
        #15 clk = 1; #15 clk = 0; 
        #15 clk = 1; #15 clk = 0; 
        #15 clk = 1; #15 clk = 0; 
        #15 clk = 1; #15 clk = 0; 
        #15 clk = 1; #15 clk = 0; 
        #15 clk = 1; #15 clk = 0; 
        #15 clk = 1; #15 clk = 0; 
        #15 clk = 1; #15 clk = 0; 
        #15 clk = 1; #15 clk = 0; 
        #15 clk = 1; #15 clk = 0; 
        #15 clk = 1; #15 clk = 0; 
        #15 clk = 1; #15 clk = 0; 
        #15 clk = 1; #15 clk = 0; 
        #15 clk = 1; #15 clk = 0; 
        #15 clk = 1; #15 clk = 0; 
        #15 clk = 1; #15 clk = 0; 
        #15 clk = 1; #15 clk = 0; 
        #15 clk = 1; #15 clk = 0; 
        #15 clk = 1; #15 clk = 0; 
        #15 clk = 1; #15 clk = 0; 
        #15 clk = 1; #15 clk = 0; 
        #15 clk = 1; #15 clk = 0; 
        #15 clk = 1; #15 clk = 0; 
        #15 clk = 1; #15 clk = 0; 
        #15 clk = 1; #15 clk = 0; 
        #15 clk = 1; #15 clk = 0; 
        #15 clk = 1; #15 clk = 0; 
        #15 clk = 1; #15 clk = 0; 
        #15 clk = 1; #15 clk = 0; 
        #15 clk = 1; #15 clk = 0; 
        #15 clk = 1; #15 clk = 0; 
        #15 clk = 1; #15 clk = 0; 
        #15 clk = 1; #15 clk = 0; 
        #15 clk = 1; #15 clk = 0; 
        #15 clk = 1; #15 clk = 0; 
        #15 clk = 1; #15 clk = 0; 
        #15 clk = 1; #15 clk = 0; 
        #15 clk = 1; #15 clk = 0; 
        #15 clk = 1; #15 clk = 0; 
        #15 clk = 1; #15 clk = 0; 
        #15 clk = 1; #15 clk = 0; 
        #15 clk = 1; #15 clk = 0; 
        #15 clk = 1; #15 clk = 0; 
        #15 clk = 1; #15 clk = 0; 
        #15 clk = 1; #15 clk = 0; 
        #15 clk = 1; #15 clk = 0; 
        #15 clk = 1; #15 clk = 0; 
        #15 clk = 1; #15 clk = 0; 
        #15 clk = 1; #15 clk = 0; 
        #15 clk = 1; #15 clk = 0; 
        #15 clk = 1; #15 clk = 0; 
        #15 clk = 1; #15 clk = 0; 
        #15 clk = 1; #15 clk = 0; 
        #15 clk = 1; #15 clk = 0; 
        #15 clk = 1; #15 clk = 0; 
        #15 clk = 1; #15 clk = 0; 
        #15 clk = 1; #15 clk = 0; 
        #15 clk = 1; #15 clk = 0; 
        #15 clk = 1; #15 clk = 0; 
        #15 clk = 1; #15 clk = 0; 
        #15 clk = 1; #15 clk = 0; 
        #15 clk = 1; #15 clk = 0; 
        #15 clk = 1; #15 clk = 0; 
        #15 clk = 1; #15 clk = 0; 
        #15 clk = 1; #15 clk = 0; 
        #15 clk = 1; #15 clk = 0; 
        #15 clk = 1; #15 clk = 0; 
        #15 clk = 1; #15 clk = 0; 
        #15 clk = 1; #15 clk = 0; 
        #15 clk = 1; #15 clk = 0; 
        #15 clk = 1; #15 clk = 0; 
        #15 clk = 1; #15 clk = 0; 
        #15 clk = 1; #15 clk = 0; 
        #15 clk = 1; #15 clk = 0; 
        #15 clk = 1; #15 clk = 0; 
        #15 clk = 1; #15 clk = 0; 
        #15 clk = 1; #15 clk = 0; 
        #15 clk = 1; #15 clk = 0; 
        #15 clk = 1; #15 clk = 0; 
        #15 clk = 1; #15 clk = 0; 
        #15 clk = 1; #15 clk = 0; 
        #15 clk = 1; #15 clk = 0; 
        #15 clk = 1; #15 clk = 0; 
        #15 clk = 1; #15 clk = 0; 
        #15 clk = 1; #15 clk = 0; 
        #15 clk = 1; #15 clk = 0; 
        #15 clk = 1; #15 clk = 0; 
        #15 clk = 1; #15 clk = 0; 
        #15 clk = 1; #15 clk = 0; 
        #15 clk = 1; #15 clk = 0; 
        #15 clk = 1; #15 clk = 0; 
        #15 clk = 1; #15 clk = 0; 
        #15 clk = 1; #15 clk = 0; 
        #15 clk = 1; #15 clk = 0; 
        #15 clk = 1; #15 clk = 0; 
        #15 clk = 1; #15 clk = 0; 
        #15 clk = 1; #15 clk = 0; 
        #15 clk = 1; #15 clk = 0; 
        #15 clk = 1; #15 clk = 0; 
        #15 clk = 1; #15 clk = 0; 
        #15 clk = 1; #15 clk = 0; 
        #15 clk = 1; #15 clk = 0; 
        #15 clk = 1; #15 clk = 0; 
        #15 clk = 1; #15 clk = 0; 
        #15 clk = 1; #15 clk = 0; 
        #15 clk = 1; #15 clk = 0; 
        #15 clk = 1; #15 clk = 0; 
        #15 clk = 1; #15 clk = 0; 
        #15 clk = 1; #15 clk = 0; 
        #15 clk = 1; #15 clk = 0; 
        #15 clk = 1; #15 clk = 0; 
        #15 clk = 1; #15 clk = 0; 
        #15 clk = 1; #15 clk = 0; 
        #15 clk = 1; #15 clk = 0; 
        #15 clk = 1; #15 clk = 0; 
        #15 clk = 1; #15 clk = 0; 
        #15 clk = 1; #15 clk = 0; 
        #15 clk = 1; #15 clk = 0; 
        #15 clk = 1; #15 clk = 0; 
        #15 clk = 1; #15 clk = 0; 
        #15 clk = 1; #15 clk = 0; 
        #15 clk = 1; #15 clk = 0; 
        #15 clk = 1; #15 clk = 0; 
        #15 clk = 1; #15 clk = 0; 
        #15 clk = 1; #15 clk = 0; 
        #15 clk = 1; #15 clk = 0; 
        #15 clk = 1; #15 clk = 0; 
        #15 clk = 1; #15 clk = 0; 
        #15 clk = 1; #15 clk = 0; 
        #15 clk = 1; #15 clk = 0; 
        #15 clk = 1; #15 clk = 0; 
        #15 clk = 1; #15 clk = 0; 
        #15 clk = 1; #15 clk = 0; 
        #15 clk = 1; #15 clk = 0; 
        #15 clk = 1; #15 clk = 0; 
        #15 clk = 1; #15 clk = 0; 
        #15 clk = 1; #15 clk = 0; 
        #15 clk = 1; #15 clk = 0; 
        #15 clk = 1; #15 clk = 0; 
        #15 clk = 1; #15 clk = 0; 
        #15 clk = 1; #15 clk = 0; 
        #15 clk = 1; #15 clk = 0; 
        #15 clk = 1; #15 clk = 0; 
        #15 clk = 1; #15 clk = 0; 
        #15 clk = 1; #15 clk = 0; 
        #15 clk = 1; #15 clk = 0; 
        #15 clk = 1; #15 clk = 0; 
        #15 clk = 1; #15 clk = 0; 
        #15 clk = 1; #15 clk = 0; 
        #15 clk = 1; #15 clk = 0; 
        #15 clk = 1; #15 clk = 0; 
        #15 clk = 1; #15 clk = 0; 
        #15 clk = 1; #15 clk = 0; 
        #15 clk = 1; #15 clk = 0; 
        #15 clk = 1; #15 clk = 0; 
        #15 clk = 1; #15 clk = 0; 
        #15 clk = 1; #15 clk = 0; 
        #15 clk = 1; #15 clk = 0; 
        #15 clk = 1; #15 clk = 0; 
        #15 clk = 1; #15 clk = 0; 
        #15 clk = 1; #15 clk = 0; 
        #15 clk = 1; #15 clk = 0; 
        #15 clk = 1; #15 clk = 0; 
        #15 clk = 1; #15 clk = 0; 
        #15 clk = 1; #15 clk = 0; 
        #15 clk = 1; #15 clk = 0; 
        #15 clk = 1; #15 clk = 0; 
        #15 clk = 1; #15 clk = 0; 
        #15 clk = 1; #15 clk = 0; 
        #15 clk = 1; #15 clk = 0; 
        #15 clk = 1; #15 clk = 0; 
        #15 clk = 1; #15 clk = 0; 
        #15 clk = 1; #15 clk = 0; 
        #15 clk = 1; #15 clk = 0; 
        #15 clk = 1; #15 clk = 0; 
        #15 clk = 1; #15 clk = 0; 
        #15 clk = 1; #15 clk = 0; 
        #15 clk = 1; #15 clk = 0; 
        #15 clk = 1; #15 clk = 0; 
        #15 clk = 1; #15 clk = 0; 
        #15 clk = 1; #15 clk = 0; 
        #15 clk = 1; #15 clk = 0; 
        #15 clk = 1; #15 clk = 0; 
        #15 clk = 1; #15 clk = 0; 
        #15 clk = 1; #15 clk = 0; 
        #15 clk = 1; #15 clk = 0; 
        #15 clk = 1; #15 clk = 0; 
        #15 clk = 1; #15 clk = 0; 
        #15 clk = 1; #15 clk = 0; 
        #15 clk = 1; #15 clk = 0; 
        #15 clk = 1; #15 clk = 0; 
        #15 clk = 1; #15 clk = 0; 
        #15 clk = 1; #15 clk = 0; 

    end

    initial
        $monitor("clk: %b", clk);
endmodule

test/vcd/Uart.vcd
$date
	Thu Dec 14 02:36:46 2023
$end
$version
	Icarus Verilog
$end
$timescale
	1s
$end
$scope module Uart_tb $end
$var wire 1 ! tx $end
$var wire 8 " Data [7:0] $end
$var reg 1 # clk $end
$var reg 1 $ readEnable $end
$var reg 2 % regselect [1:0] $end
$var reg 1 & reset $end
$var reg 1 ' rx $end
$var reg 8 ( writeData [7:0] $end
$var reg 1 ) writeEnable $end
$scope module uart $end
$var wire 1 # clk $end
$var wire 1 $ readEnable $end
$var wire 2 * regSelect [1:0] $end
$var wire 1 & reset $end
$var wire 1 ' rx $end
$var wire 8 + writeData [7:0] $end
$var wire 1 ) writeEnable $end
$var wire 1 ! tx $end
$var wire 1 , busy $end
$var parameter 32 - DATA_BITS $end
$var parameter 32 . DIVISOR $end
$var parameter 32 / STOP_BITS $end
$var reg 8 0 Data [7:0] $end
$var reg 1 1 baud_clk $end
$var reg 7 2 baud_counter [6:0] $end
$var reg 8 3 control [7:0] $end
$var reg 8 4 data [7:0] $end
$var reg 3 5 data_index [2:0] $end
$scope module transmitter $end
$var wire 8 6 Data [7:0] $end
$var wire 1 1 baud_clk $end
$var wire 1 & reset $end
$var wire 1 7 start $end
$var parameter 32 8 DATA_BITS $end
$var parameter 2 9 s_DATA $end
$var parameter 2 : s_IDLE $end
$var parameter 2 ; s_START $end
$var parameter 2 < s_STOP $end
$var reg 1 , busy $end
$var reg 3 = data_index [2:0] $end
$var reg 2 > state [1:0] $end
$var reg 1 ! tx $end
$upscope $end
$upscope $end
$upscope $end
$enddefinitions $end
$comment Show the parameter values. $end
$dumpall
b11 <
b1 ;
b0 :
b10 9
b1000 8
b1 /
b100 .
b1000 -
$end
#0
$dumpvars
b0 >
b0 =
x7
b1001000 6
b0 5
b1001000 4
bx 3
b0 2
01
bx 0
x,
bx +
bx *
x)
bx (
x'
x&
bx %
x$
x#
bx "
x!
$end
#15
0&
0#
#30
07
0,
1!
b0 3
b0 4
b0 6
1&
1#
#45
0&
0#
#60
b1 2
1#
#75
b0 %
b0 *
b10101010 (
b10101010 +
1)
0#
#90
b0 2
11
b10101010 4
b10101010 6
1#
#105
b10 %
b10 *
b1 (
b1 +
0#
#120
17
b1 3
b1 2
1#
#135
0)
0#
#150
b0 2
01
1#
#165
0#
#180
b1 2
1#
#195
0#
#210
b1 >
b0 2
11
1#
#225
0#
#240
b1 2
1#
#255
0#
#270
b0 2
01
1#
#285
0#
#300
b1 2
1#
#315
0#
#330
1,
b10 >
0!
b0 2
11
1#
#345
0#
#360
07
b0 3
b1 2
1#
#375
0#
#390
b0 2
01
1#
#405
0#
#420
b1 2
1#
#435
0#
#450
b1 =
b0 2
11
1#
#465
0#
#480
b1 2
1#
#495
0#
#510
b0 2
01
1#
#525
0#
#540
b1 2
1#
#555
0#
#570
b10 =
1!
b0 2
11
1#
#585
0#
#600
b1 2
1#
#615
0#
#630
b0 2
01
1#
#645
0#
#660
b1 2
1#
#675
0#
#690
b11 =
0!
b0 2
11
1#
#705
0#
#720
b1 2
1#
#735
0#
#750
b0 2
01
1#
#765
0#
#780
b1 2
1#
#795
0#
#810
b100 =
1!
b0 2
11
1#
#825
0#
#840
b1 2
1#
#855
0#
#870
b0 2
01
1#
#885
0#
#900
b1 2
1#
#915
0#
#930
b101 =
0!
b0 2
11
1#
#945
0#
#960
b1 2
1#
#975
0#
#990
b0 2
01
1#
#1005
0#
#1020
b1 2
1#
#1035
0#
#1050
b110 =
1!
b0 2
11
1#
#1065
0#
#1080
b1 2
1#
#1095
0#
#1110
b0 2
01
1#
#1125
0#
#1140
b1 2
1#
#1155
0#
#1170
b111 =
0!
b0 2
11
1#
#1185
0#
#1200
b1 2
1#
#1215
0#
#1230
b0 2
01
1#
#1245
0#
#1260
b1 2
1#
#1275
0#
#1290
b0 =
b11 >
1!
b0 2
11
1#
#1305
0#
#1320
b1 2
1#
#1335
0#
#1350
b0 2
01
1#
#1365
0#
#1380
b1 2
1#
#1395
0#
#1410
0,
b0 >
b0 2
11
1#
#1425
0#
#1440
b1 2
1#
#1455
0#
#1470
b0 2
01
1#
#1485
0#
#1500
b1 2
1#
#1515
0#
#1530
b0 2
11
1#
#1545
0#
#1560
b1 2
1#
#1575
0#
#1590
b0 2
01
1#
#1605
0#
#1620
b1 2
1#
#1635
0#
#1650
b0 2
11
1#
#1665
0#
#1680
b1 2
1#
#1695
0#
#1710
b0 2
01
1#
#1725
0#
#1740
b1 2
1#
#1755
0#
#1770
b0 2
11
1#
#1785
0#
#1800
b1 2
1#
#1815
0#
#1830
b0 2
01
1#
#1845
0#
#1860
b1 2
1#
#1875
0#
#1890
b0 2
11
1#
#1905
0#
#1920
b1 2
1#
#1935
0#
#1950
b0 2
01
1#
#1965
0#
#1980
b1 2
1#
#1995
0#
#2010
b0 2
11
1#
#2025
0#
#2040
b1 2
1#
#2055
0#
#2070
b0 2
01
1#
#2085
0#
#2100
b1 2
1#
#2115
0#
#2130
b0 2
11
1#
#2145
0#
#2160
b1 2
1#
#2175
0#
#2190
b0 2
01
1#
#2205
0#
#2220
b1 2
1#
#2235
0#
#2250
b0 2
11
1#
#2265
0#
#2280
b1 2
1#
#2295
0#
#2310
b0 2
01
1#
#2325
0#
#2340
b1 2
1#
#2355
0#
#2370
b0 2
11
1#
#2385
0#
#2400
b1 2
1#
#2415
0#
#2430
b0 2
01
1#
#2445
0#
#2460
b1 2
1#
#2475
0#
#2490
b0 2
11
1#
#2505
0#
#2520
b1 2
1#
#2535
0#
#2550
b0 2
01
1#
#2565
0#
#2580
b1 2
1#
#2595
0#
#2610
b0 2
11
1#
#2625
0#
#2640
b1 2
1#
#2655
0#
#2670
b0 2
01
1#
#2685
0#
#2700
b1 2
1#
#2715
0#
#2730
b0 2
11
1#
#2745
0#
#2760
b1 2
1#
#2775
0#
#2790
b0 2
01
1#
#2805
0#
#2820
b1 2
1#
#2835
0#
#2850
b0 2
11
1#
#2865
0#
#2880
b1 2
1#
#2895
0#
#2910
b0 2
01
1#
#2925
0#
#2940
b1 2
1#
#2955
0#
#2970
b0 2
11
1#
#2985
0#
#3000
b1 2
1#
#3015
0#
#3030
b0 2
01
1#
#3045
0#
#3060
b1 2
1#
#3075
0#
#3090
b0 2
11
1#
#3105
0#
#3120
b1 2
1#
#3135
0#
#3150
b0 2
01
1#
#3165
0#
#3180
b1 2
1#
#3195
0#
#3210
b0 2
11
1#
#3225
0#
#3240
b1 2
1#
#3255
0#
#3270
b0 2
01
1#
#3285
0#
#3300
b1 2
1#
#3315
0#
#3330
b0 2
11
1#
#3345
0#
#3360
b1 2
1#
#3375
0#
#3390
b0 2
01
1#
#3405
0#
#3420
b1 2
1#
#3435
0#
#3450
b0 2
11
1#
#3465
0#
#3480
b1 2
1#
#3495
0#
#3510
b0 2
01
1#
#3525
0#
#3540
b1 2
1#
#3555
0#
#3570
b0 2
11
1#
#3585
0#
#3600
b1 2
1#
#3615
0#
#3630
b0 2
01
1#
#3645
0#
#3660
b1 2
1#
#3675
0#
#3690
b0 2
11
1#
#3705
0#
#3720
b1 2
1#
#3735
0#
#3750
b0 2
01
1#
#3765
0#
#3780
b1 2
1#
#3795
0#
#3810
b0 2
11
1#
#3825
0#
#3840
b1 2
1#
#3855
0#
#3870
b0 2
01
1#
#3885
0#
#3900
b1 2
1#
#3915
0#
#3930
b0 2
11
1#
#3945
0#
#3960
b1 2
1#
#3975
0#
#3990
b0 2
01
1#
#4005
0#
#4020
b1 2
1#
#4035
0#
#4050
b0 2
11
1#
#4065
0#
#4080
b1 2
1#
#4095
0#
#4110
b0 2
01
1#
#4125
0#
#4140
b1 2
1#
#4155
0#
#4170
b0 2
11
1#
#4185
0#
#4200
b1 2
1#
#4215
0#
#4230
b0 2
01
1#
#4245
0#
#4260
b1 2
1#
#4275
0#
#4290
b0 2
11
1#
#4305
0#
#4320
b1 2
1#
#4335
0#
#4350
b0 2
01
1#
#4365
0#
#4380
b1 2
1#
#4395
0#
#4410
b0 2
11
1#
#4425
0#
#4440
b1 2
1#
#4455
0#
#4470
b0 2
01
1#
#4485
0#
#4500
b1 2
1#
#4515
0#
#4530
b0 2
11
1#
#4545
0#
#4560
b1 2
1#
#4575
0#
#4590
b0 2
01
1#
#4605
0#
#4620
b1 2
1#
#4635
0#
#4650
b0 2
11
1#
#4665
0#
#4680
b1 2
1#
#4695
0#
#4710
b0 2
01
1#
#4725
0#
#4740
b1 2
1#
#4755
0#
#4770
b0 2
11
1#
#4785
0#
#4800
b1 2
1#
#4815
0#
#4830
b0 2
01
1#
#4845
0#
#4860
b1 2
1#
#4875
0#
#4890
b0 2
11
1#
#4905
0#
#4920
b1 2
1#
#4935
0#
#4950
b0 2
01
1#
#4965
0#
#4980
b1 2
1#
#4995
0#
#5010
b0 2
11
1#
#5025
0#
#5040
b1 2
1#
#5055
0#
#5070
b0 2
01
1#
#5085
0#
#5100
b1 2
1#
#5115
0#
#5130
b0 2
11
1#
#5145
0#
#5160
b1 2
1#
#5175
0#
#5190
b0 2
01
1#
#5205
0#
#5220
b1 2
1#
#5235
0#
#5250
b0 2
11
1#
#5265
0#
#5280
b1 2
1#
#5295
0#
#5310
b0 2
01
1#
#5325
0#
#5340
b1 2
1#
#5355
0#
#5370
b0 2
11
1#
#5385
0#
#5400
b1 2
1#
#5415
0#
#5430
b0 2
01
1#
#5445
0#
#5460
b1 2
1#
#5475
0#
#5490
b0 2
11
1#
#5505
0#
#5520
b1 2
1#
#5535
0#
#5550
b0 2
01
1#
#5565
0#
#5580
b1 2
1#
#5595
0#
#5610
b0 2
11
1#
#5625
0#
#5640
b1 2
1#
#5655
0#
#5670
b0 2
01
1#
#5685
0#
#5700
b1 2
1#
#5715
0#
#5730
b0 2
11
1#
#5745
0#
#5760
b1 2
1#
#5775
0#
#5790
b0 2
01
1#
#5805
0#
#5820
b1 2
1#
#5835
0#
#5850
b0 2
11
1#
#5865
0#
#5880
b1 2
1#
#5895
0#
#5910
b0 2
01
1#
#5925
0#
#5940
b1 2
1#
#5955
0#
#5970
b0 2
11
1#
#5985
0#
#6000
b1 2
1#
#6015
0#
#6030
b0 2
01
1#
#6045
0#
#6060
b1 2
1#
#6075
0#
#6090
b0 2
11
1#
#6105
0#
#6120
b1 2
1#
#6135
0#
#6150
b0 2
01
1#
#6165
0#
#6180
b1 2
1#
#6195
0#
#6210
b0 2
11
1#
#6225
0#
#6240
b1 2
1#
#6255
0#
#6270
b0 2
01
1#
#6285
0#
#6300
b1 2
1#
#6315
0#
#6330
b0 2
11
1#
#6345
0#
#6360
b1 2
1#
#6375
0#
#6390
b0 2
01
1#
#6405
0#
#6420
b1 2
1#
